bandit_formatter_junit/__init__.py
bandit_formatter_junit/junit.py
bandit_formatter_junit-0.2.0.dist-info/entry_points.txt
bandit_formatter_junit-0.2.0.dist-info/LICENSE
bandit_formatter_junit-0.2.0.dist-info/WHEEL
bandit_formatter_junit-0.2.0.dist-info/METADATA
bandit_formatter_junit-0.2.0.dist-info/RECORD
