Metadata-Version: 2.1
Name: bandit-formatter-junit
Version: 0.2.0
Summary: A bandit formatter plugin for valid JUnit output
License: MIT
Author: Martin Styk
Author-email: mart.styk@gmail.com
Requires-Python: >=3.6,<4.0
Classifier: License :: OSI Approved :: MIT License
Classifier: Programming Language :: Python :: 3
Classifier: Programming Language :: Python :: 3.6
Classifier: Programming Language :: Python :: 3.7
Classifier: Programming Language :: Python :: 3.8
Classifier: Programming Language :: Python :: 3.9
Requires-Dist: bandit (>=1.7.0,<2.0.0)
